king/CompleteSearchResponse.py
king/Config.py
king/DataClass.py
king/Diy.py
king/Downloader.py
king/Image.py
king/King.py
king/MusicInfo.py
king/TipResponse.py
king/Tracker.py
king/__init__.py
king/main.py
king/yinxiao.py
foyou_king-0.0.3.dist-info/LICENSE
foyou_king-0.0.3.dist-info/METADATA
foyou_king-0.0.3.dist-info/WHEEL
foyou_king-0.0.3.dist-info/entry_points.txt
foyou_king-0.0.3.dist-info/top_level.txt
foyou_king-0.0.3.dist-info/RECORD
