Metadata-Version: 2.1
Name: foyou-king
Version: 0.0.3
Summary: search & download kugou-rings
Author: foyoux
Project-URL: Source, https://github.com/foyoux/foyou-king
Project-URL: Homepage, https://github.com/foyoux/foyou-king
Project-URL: Bug Tracker, https://github.com/foyoux/foyou-king/issues
Keywords: foyou-king
Classifier: Programming Language :: Python
Classifier: Programming Language :: Python :: 3
Classifier: Programming Language :: Python :: 3.7
Classifier: Programming Language :: Python :: 3.8
Classifier: Programming Language :: Python :: 3.9
Classifier: Programming Language :: Python :: 3.10
Classifier: Programming Language :: Python :: 3.11
Requires-Python: >=3.7
License-File: LICENSE
Requires-Dist: requests
Requires-Dist: coloredlogs
Requires-Dist: tqdm
Requires-Dist: fire
Requires-Dist: typing-extensions
Requires-Dist: parsel
Requires-Dist: urllib3
